{
  "creds": {
    "noiseKey": {
      "private": {
        "type": "Buffer",
        "data": "WAFdIDyvaxWga1wFdyWmWkleEltAjHlG3B+Q7t1Ub34="
      },
      "public": {
        "type": "Buffer",
        "data": "FmbqCLknxnjO23RzqmZL0g7NkCFBdLLwscd6KvQoUA8="
      }
    },
    "signedIdentityKey": {
      "private": {
        "type": "Buffer",
        "data": "KGxZc9XBjuZ8tlqWDI0SPYFxIsxuw6Y67qj1vWnJd0I="
      },
      "public": {
        "type": "Buffer",
        "data": "8o5lPJAXi7s5k0FZlWIUaaspJfjmU2bLey2AyTV/MRc="
      }
    },
    "signedPreKey": {
      "keyPair": {
        "private": {
          "type": "Buffer",
          "data": "qFygf1gMbROG4mruBZX40577vDvb7QlMqdSNbbD4kU0="
        },
        "public": {
          "type": "Buffer",
          "data": "7NSzZWFv3bCA1KAD3xtkuigr5wMum/ZdwZNyVo+TkDk="
        }
      },
      "signature": {
        "type": "Buffer",
        "data": "58vV4awoK/YuOPsIGGUc0tjJZ3rnh/QXHV8L4QDxahvgnSny1YFUxvr4e4Q8xDbnsFKOigHH+WqUISZfRA90Aw=="
      },
      "keyId": 1
    },
    "registrationId": 42,
    "advSecretKey": "O/gaBPdpS9LrC/xRGEU7xqh9QFK49gx/rvsZmmM2yTA=",
    "processedHistoryMessages": [
      {
        "key": {
          "remoteJid": "6281327238906@s.whatsapp.net",
          "fromMe": true,
          "id": "AA0FBFE85FB798C1F81DD3A063CED944"
        },
        "messageTimestamp": 1678883045
      },
      {
        "key": {
          "remoteJid": "6281327238906@s.whatsapp.net",
          "fromMe": true,
          "id": "CC844D96BF421169FB121A6AD974ADE2"
        },
        "messageTimestamp": 1678883046
      },
      {
        "key": {
          "remoteJid": "6281327238906@s.whatsapp.net",
          "fromMe": true,
          "id": "46227BF97347F33EA58A681FC95821B4"
        },
        "messageTimestamp": 1678883055
      }
    ],
    "nextPreKeyId": 32,
    "firstUnuploadedPreKeyId": 32,
    "accountSyncCounter": 1,
    "accountSettings": {
      "unarchiveChats": false
    },
    "account": {
      "details": "CLqOl/sFEOLxxqAGGAE=",
      "accountSignatureKey": "sT2XLPN152vMBX8soi8czNzVyehCRylw80ZUP5ijeFo=",
      "accountSignature": "h6192lDG7yremsaXB4nxBWlWxlLnUkS2pa8XusgzOyXCKa6V3w1fWoD+8n03D/sEMz5ni4rmOpXbaXDnXfjLCQ==",
      "deviceSignature": "yOWFXGSOY/dScekN8LWT2AD/7V2jX89ebvr18q2ursg+sN5pobQ0dfPRSgQC1SrVnIgETybUnlfpu/KizrT/BQ=="
    },
    "me": {
      "id": "6281327238906:28@s.whatsapp.net",
      "name": "𝙕𝘼𝙇𝙇𝙭𝘽𝙊𝙏𝙕 𝙑2",
      "jid": "6281327238906@s.whatsapp.net"
    },
    "signalIdentities": [
      {
        "identifier": {
          "name": "6281327238906:28@s.whatsapp.net",
          "deviceId": 0
        },
        "identifierKey": {
          "type": "Buffer",
          "data": "BbE9lyzzdedrzAV/LKIvHMzc1cnoQkcpcPNGVD+Yo3ha"
        }
      }
    ],
    "platform": "android",
    "lastAccountSyncTimestamp": 1678883044,
    "myAppStateKeyId": "AAAAAKeP"
  },
  "keys": {
    "preKeys": {
      "1": {
        "private": {
          "type": "Buffer",
          "data": "qKI6M2JDEfsB0NKr4Tk0ku0GD3iVB/+MGBzeTHhZ4Hw="
        },
        "public": {
          "type": "Buffer",
          "data": "5Kx2UXhacCbmn7HG9C0RiSTfx527ex0GybbonugfTW4="
        }
      },
      "2": {
        "private": {
          "type": "Buffer",
          "data": "UKJsN8IUwdLKe3DvEIIi5m2fdTvlvGM7ctpuni7Gd2I="
        },
        "public": {
          "type": "Buffer",
          "data": "EJ8KhFir0IEGMjmkXJOMT9Ujwioza0F5k5L03A5DZgo="
        }
      },
      "3": {
        "private": {
          "type": "Buffer",
          "data": "YB+WoNZNWqVHZdST6B6etQihqc/tu9kaVNa5UChzpUk="
        },
        "public": {
          "type": "Buffer",
          "data": "VYVUE2aX5QXH0mitFt/UOZOm7uIySsBFwrPcFiHIZl0="
        }
      },
      "4": {
        "private": {
          "type": "Buffer",
          "data": "yFHmeE2VbzU7g6Gacm8Xx9gAhrvmF+Fo149ehxZ7W2A="
        },
        "public": {
          "type": "Buffer",
          "data": "YkoFHw1WW5NGwgYQpmxD1ui8d/rLOjtHHXzfLUAUrw8="
        }
      },
      "5": {
        "private": {
          "type": "Buffer",
          "data": "WHWOGhE8sdl+XI2gM1DB+NZwbr44CfxJ43lRtxRB4Gs="
        },
        "public": {
          "type": "Buffer",
          "data": "go50njRExYve/GbMf2YXdM6ZyiQNKWPBI4SFZiIprgw="
        }
      },
      "6": {
        "private": {
          "type": "Buffer",
          "data": "8CegMOz4KTqlLpVuwmfEC+eS8EFMCUASoh+Liw+vPWE="
        },
        "public": {
          "type": "Buffer",
          "data": "zFtCWxfjAnzJm1dev2HlRh5XiZOgf4SM8SAKRlJC63I="
        }
      },
      "7": {
        "private": {
          "type": "Buffer",
          "data": "ILz61AH2s52aGe36IcoUMr1uE1w5OBJIgO5qB2gu1Xw="
        },
        "public": {
          "type": "Buffer",
          "data": "oDkd5T42iGXITe9cUxI3njdj9q5RaKxQUCnrPIoK3VI="
        }
      },
      "8": {
        "private": {
          "type": "Buffer",
          "data": "2NRcNOArT93929T3P2lowIzHhnBjkX0k7ehkaS013V0="
        },
        "public": {
          "type": "Buffer",
          "data": "bwYeeMpid4n4IL4iIcnFLvW2x+ZkwmflvE8eEkgG8hY="
        }
      },
      "9": {
        "private": {
          "type": "Buffer",
          "data": "YKrG53HGrjlGqiN51P+fTvP8+1cEO7U3wV6YcYveXnM="
        },
        "public": {
          "type": "Buffer",
          "data": "Vk9DO6AEI7R933o2TndKCnMHxYd0QzKoRmkfYNdGRSw="
        }
      },
      "10": {
        "private": {
          "type": "Buffer",
          "data": "YNHdoQMQaH8NSVBJDJZhYryyIVlrYZIpgqoHFcF5fGc="
        },
        "public": {
          "type": "Buffer",
          "data": "QY3Ql+7Br+CxRu6z/CUpDPmw0ktm3JnFo07sm4Z9bDQ="
        }
      },
      "11": null,
      "12": {
        "private": {
          "type": "Buffer",
          "data": "CFRQL2p2hMl4qdGiuupNDvyU53FAM+YP2fTOnOp1ZHI="
        },
        "public": {
          "type": "Buffer",
          "data": "VCdTLNzNbx/GOO2zMUEXOYqMEgDxpDvuH61iExJhiCA="
        }
      },
      "13": {
        "private": {
          "type": "Buffer",
          "data": "mI1uDD0jScxqPRkeI/VZJuubREI4XSqOzs5P2+f9LU0="
        },
        "public": {
          "type": "Buffer",
          "data": "Ob09vfY6X4c8o/wR3HQmkHoUGqxuYkDAnkAgMN4hAww="
        }
      },
      "14": {
        "private": {
          "type": "Buffer",
          "data": "gD35Wnqbcj9/gEoDIZF6MWSfVM9id+roo5ui75CdRmY="
        },
        "public": {
          "type": "Buffer",
          "data": "W0Xa0Gyq44chJM27/H5z67o1UejCczrQbSW/LCcZ9mQ="
        }
      },
      "15": {
        "private": {
          "type": "Buffer",
          "data": "QG32XsUZzfe19j6sGHQ2qrdZYK7gvP0cE9mN2JD6sWI="
        },
        "public": {
          "type": "Buffer",
          "data": "9bJkhZyHW3wlZT8xS9bOw0+Ag6anlv4Mzyc7HtA25Hw="
        }
      },
      "16": {
        "private": {
          "type": "Buffer",
          "data": "aPyU8YFW2MaNfvYDoPYjsFENaCCfnguqarE/i3sDPWU="
        },
        "public": {
          "type": "Buffer",
          "data": "TUetUD9i5tIdvThbC2o54y7znS9/ii59SQLlL+QyBEE="
        }
      },
      "17": {
        "private": {
          "type": "Buffer",
          "data": "OFCrp83L4SGewTBQaBgu4cMVYNv1XvFaiWzpMaee/2E="
        },
        "public": {
          "type": "Buffer",
          "data": "mppGdwvXhHeLh2MsFgPYeHP1V1E7Ks/ZygQIYNbe9no="
        }
      },
      "18": {
        "private": {
          "type": "Buffer",
          "data": "aBMsCd2Sv0DfdmsSTSiuX9HAy7i1DRvME/p+7yELeFw="
        },
        "public": {
          "type": "Buffer",
          "data": "gCizy04cxCXAP3xXSaI26UzLw99CUjM+feGjGQwIoGU="
        }
      },
      "19": {
        "private": {
          "type": "Buffer",
          "data": "OII7Bb4of37N2WK57/q1SAHpprMltmb4BQGuYnL07W0="
        },
        "public": {
          "type": "Buffer",
          "data": "HqsEEYRCxfWa8nEYogiWEpfAz8u/9J643zrLF3/aHFY="
        }
      },
      "20": {
        "private": {
          "type": "Buffer",
          "data": "OApCV287Z+34REfuWFSZ8r+ZP5T7O/Ay4JKbQL0KcEU="
        },
        "public": {
          "type": "Buffer",
          "data": "w0l44z6aSvI+tt0olVsXVxFAAkphq9bsSVq2m0KNhHY="
        }
      },
      "21": {
        "private": {
          "type": "Buffer",
          "data": "cENBHYHBG3fk0fGczz2FU32chYHiC+v2U/FijCeBDXI="
        },
        "public": {
          "type": "Buffer",
          "data": "LArn3oDHZo5Q34LPdeIInbmgcAR8UESiGviqjHXiCUM="
        }
      },
      "22": {
        "private": {
          "type": "Buffer",
          "data": "CD1giW+wJT91g4m1wnji//BbMMJ2n5EjtLUnSa5AWk8="
        },
        "public": {
          "type": "Buffer",
          "data": "uhWNl5dlAPayoTg08Lai0xriekwjI6zGyKEtpW4e2wU="
        }
      },
      "23": {
        "private": {
          "type": "Buffer",
          "data": "gL9pA7VpJwSfuG5a6ULu732SNfCcZ/I7O08qeVdmmEk="
        },
        "public": {
          "type": "Buffer",
          "data": "F2lY4QJVDUKcynJoSIpKgmKXwb/FhPl0jc7SDpcV2RY="
        }
      },
      "24": {
        "private": {
          "type": "Buffer",
          "data": "eAKvCvpA7l0uwBwRjkOS6A+g/qQJw7dWk+ThjhVxjG4="
        },
        "public": {
          "type": "Buffer",
          "data": "BjAsLY+6ITpOe+214I+6wjzUzePe6m0hde4Etqri/DQ="
        }
      },
      "25": {
        "private": {
          "type": "Buffer",
          "data": "COmE7vlDBExt4wNJkpMCfSNxjtMMy3WjyqyPgWGSlmU="
        },
        "public": {
          "type": "Buffer",
          "data": "y8rcLUBGqovU2XqqNKL5r0BhK6EwAn4yEjym0kSBEmw="
        }
      },
      "26": {
        "private": {
          "type": "Buffer",
          "data": "oISpK/YH1AeixjWVzxYg3v2KCwfHiLZgHu/HnEkDwmE="
        },
        "public": {
          "type": "Buffer",
          "data": "F5uaCK6QYbCMjy45i3LbF7L19F3Z/iRMfSZ8ZydErEA="
        }
      },
      "27": {
        "private": {
          "type": "Buffer",
          "data": "qJqv6YssVA/zJqGjTl4AimpIxs7nWUwvT9FyOIDGYWs="
        },
        "public": {
          "type": "Buffer",
          "data": "BaTdjpXe1zlcFgu4AcvFdUmJCSVG3pC0fSy1l2O0VAo="
        }
      },
      "28": {
        "private": {
          "type": "Buffer",
          "data": "AHMOJp+UCHGCpuH6qg2NwkeTfrWXUu2/kwu8gSpwwHQ="
        },
        "public": {
          "type": "Buffer",
          "data": "yA+6322Cm9rebf5g1xfTkYtRUpaWXXOrQjgdhYa9Igc="
        }
      },
      "29": {
        "private": {
          "type": "Buffer",
          "data": "OGASslhQSTWOnjvyw2WQi00L5qas93P+2YX5ojehOm8="
        },
        "public": {
          "type": "Buffer",
          "data": "bm4BXL88gG5FvDTCxEgFUIaH4DeN61PzsGgkC6GSNAE="
        }
      },
      "30": {
        "private": {
          "type": "Buffer",
          "data": "KOFqxCa1i0lkoUW5nzGxgThg116V2vbF/EqOg3xn82I="
        },
        "public": {
          "type": "Buffer",
          "data": "GwIwEbt6DTFOX8LiWNBAd4EU6oS1OzPAloNEgFNCqiI="
        }
      },
      "31": null
    },
    "sessions": {
      "6281327238906.0": {
        "_sessions": {
          "BddBCraws8VHXqVvNEA0gugPur+1vn+lOZTMlle+siJC": {
            "registrationId": 866430343,
            "currentRatchet": {
              "ephemeralKeyPair": {
                "pubKey": "BfVMqDuwFgt135x0qiW+9iChcHkhwJErELgzfV+oToRH",
                "privKey": "IPqBBVMPSW70Kpz9o9shb/RxorlmDZRIR84jDUAi5WY="
              },
              "lastRemoteEphemeralKey": "BXATueAjwxMI4VvCHsGpTE6hKqgFTSXiyAtm5XSmr79T",
              "previousCounter": 0,
              "rootKey": "ujxxNOUKb+ylch4z5kIYfnH2Cxb5+Q1cxT8ssiXMFi4="
            },
            "indexInfo": {
              "baseKey": "BddBCraws8VHXqVvNEA0gugPur+1vn+lOZTMlle+siJC",
              "baseKeyType": 2,
              "closed": -1,
              "used": 1678883045905,
              "created": 1678883045905,
              "remoteIdentityKey": "BbE9lyzzdedrzAV/LKIvHMzc1cnoQkcpcPNGVD+Yo3ha"
            },
            "_chains": {
              "BXATueAjwxMI4VvCHsGpTE6hKqgFTSXiyAtm5XSmr79T": {
                "chainKey": {
                  "counter": 6,
                  "key": "guEAe+vMGJaDlpwtasVCqv1U4lHuCTSCrmYB2jtJNqI="
                },
                "chainType": 2,
                "messageKeys": {}
              },
              "BfVMqDuwFgt135x0qiW+9iChcHkhwJErELgzfV+oToRH": {
                "chainKey": {
                  "counter": 4,
                  "key": "8OqcaoH0Xzq9JoaiBi2Zol200x6fWM9L+Xux4zsWij4="
                },
                "chainType": 1,
                "messageKeys": {}
              }
            }
          }
        },
        "version": "v1"
      },
      "6281333154367.0": {
        "_sessions": {
          "BRAbDaxft7kSjbWn0CgeUmlQN0+tQGRZMLdkvJoOOLVG": {
            "registrationId": 1298116795,
            "currentRatchet": {
              "ephemeralKeyPair": {
                "pubKey": "BVZAdbsDROKNWzncLTU1uKeMorj9XzmOZIRv46hUeR5S",
                "privKey": "0EczDuHhOgtbI34PjckJFkFtlrgSv5bW/7PUVz1OiHo="
              },
              "lastRemoteEphemeralKey": "BYWK1QbU6JpmvAMPleM2ZHMU7jm70TVP31wYW62+qeAS",
              "previousCounter": 0,
              "rootKey": "ov6uGz79S7bRuebYAqG0vv/7MDlXaTnCi8rYh66fCXg="
            },
            "indexInfo": {
              "baseKey": "BRAbDaxft7kSjbWn0CgeUmlQN0+tQGRZMLdkvJoOOLVG",
              "baseKeyType": 2,
              "closed": -1,
              "used": 1678883113758,
              "created": 1678883092275,
              "remoteIdentityKey": "BVlwmNTgOyEWCNqrqRJ6DPNwgkrk8C4QDeiiHDj4WpFZ"
            },
            "_chains": {
              "BYVI9F8d5SQrwzFwp5octNceI5S5vcQCm+3DjO853ol9": {
                "chainKey": {
                  "counter": 0
                },
                "chainType": 2,
                "messageKeys": {}
              },
              "BUbkUYDENgt5D8s8W9PzAjVQb2nh3DweHlpN/2HshxRv": {
                "chainKey": {
                  "counter": 0
                },
                "chainType": 2,
                "messageKeys": {}
              },
              "Bf0JWs0G91+rIynWZJcm5+SWTkYGrYl5IJ4uS+J9y25M": {
                "chainKey": {
                  "counter": 0
                },
                "chainType": 2,
                "messageKeys": {}
              },
              "BYWK1QbU6JpmvAMPleM2ZHMU7jm70TVP31wYW62+qeAS": {
                "chainKey": {
                  "counter": 0,
                  "key": "uw9nCdajdYw+Sqeiff9beZngD9yOtdX5QE1aaii5rmE="
                },
                "chainType": 2,
                "messageKeys": {}
              },
              "BVZAdbsDROKNWzncLTU1uKeMorj9XzmOZIRv46hUeR5S": {
                "chainKey": {
                  "counter": 0,
                  "key": "Z/88WiweK9naLGPxjhL/xzKL87e8HdK18nN3U25n/MI="
                },
                "chainType": 1,
                "messageKeys": {}
              }
            }
          }
        },
        "version": "v1"
      },
      "6287784028546:4.0": {
        "_sessions": {
          "BUY36jzo4QF9k/kuovmYS63JKbm6hDWL5zxSsFQmg1M6": {
            "registrationId": 130,
            "currentRatchet": {
              "ephemeralKeyPair": {
                "pubKey": "BRT0Rqd0cdJcKGjQOLzgPZmRU8103N3Ujhi/YEg2LCsB",
                "privKey": "AC06TLMp9gK1ZX3uJGUf7+vSdEK10I4JD9F1E1oEDEE="
              },
              "lastRemoteEphemeralKey": "BbDrgpU2MiTwTKJ4e8Oq0WnJtDNfdjZwjgY2YWQMU7NL",
              "previousCounter": 0,
              "rootKey": "WOVMByPkq8XJCOkKSQr+fO33fgSvfJ/mWENLeqmprD4="
            },
            "indexInfo": {
              "baseKey": "BUY36jzo4QF9k/kuovmYS63JKbm6hDWL5zxSsFQmg1M6",
              "baseKeyType": 1,
              "closed": -1,
              "used": 1678883115876,
              "created": 1678883114814,
              "remoteIdentityKey": "BQbZzprrxTRzNgo10XxxHOsiC8ewQxPx5XDBEONW7zxe"
            },
            "_chains": {
              "BbDrgpU2MiTwTKJ4e8Oq0WnJtDNfdjZwjgY2YWQMU7NL": {
                "chainKey": {
                  "counter": 0,
                  "key": "P6lc24yVulCRhu3Whm8Xb8ZYniK5Zr53AN3IgltzUCE="
                },
                "chainType": 2,
                "messageKeys": {}
              },
              "BRT0Rqd0cdJcKGjQOLzgPZmRU8103N3Ujhi/YEg2LCsB": {
                "chainKey": {
                  "counter": -1,
                  "key": "2+VWahpfZWxbS4JcTaWhAC2MiNk2fbhHThQmD5crp8w="
                },
                "chainType": 1,
                "messageKeys": {}
              }
            }
          }
        },
        "version": "v1"
      },
      "6281349838609:9.0": {
        "_sessions": {
          "BcvC1x47Bpw5dZ1q/hI78quKMfC79H/mk/PTPAHvQ14Y": {
            "registrationId": 123,
            "currentRatchet": {
              "ephemeralKeyPair": {
                "pubKey": "BadTRBrgVLNYxRN0iYAOTOpKa/nR4gtHEONsuPARXhhf",
                "privKey": "wMNFAAP1aQglHdUG7uwGT88ikZzBhN/MA05O/JCWpG4="
              },
              "lastRemoteEphemeralKey": "BXp78LeXzzyfXhJdPMs/8hAKaSk7hx3cVk/BVuAvRp16",
              "previousCounter": 0,
              "rootKey": "6oLrT6OrTuMO4+P9s0ozJFUdJZv5GduddiuSJ18qOrM="
            },
            "indexInfo": {
              "baseKey": "BcvC1x47Bpw5dZ1q/hI78quKMfC79H/mk/PTPAHvQ14Y",
              "baseKeyType": 1,
              "closed": -1,
              "used": 1678883122513,
              "created": 1678883114820,
              "remoteIdentityKey": "BSuXR+9wgCrWLPFgDgO9EubgO6zSBAkQoDT/uyQpErwA"
            },
            "_chains": {
              "BXp78LeXzzyfXhJdPMs/8hAKaSk7hx3cVk/BVuAvRp16": {
                "chainKey": {
                  "counter": 0,
                  "key": "AFfsSu4RtPb4JCgZjFq9Nw7O8XoJL7yit+/ydFlrEL0="
                },
                "chainType": 2,
                "messageKeys": {}
              },
              "BadTRBrgVLNYxRN0iYAOTOpKa/nR4gtHEONsuPARXhhf": {
                "chainKey": {
                  "counter": -1,
                  "key": "QFDtMuSIDHYbIHQRiM2JuHBp7NtZdzzMPY7Uzu6NHUA="
                },
                "chainType": 1,
                "messageKeys": {}
              }
            }
          }
        },
        "version": "v1"
      },
      "6281349838609.0": {
        "_sessions": {
          "BeBmM7DvKkTUHyjXjY8fpIiPKN2GRZOLxkdeSfIW4U9j": {
            "registrationId": 673164180,
            "currentRatchet": {
              "ephemeralKeyPair": {
                "pubKey": "Bc+1+gB6tHZuu0UeKARUu94OQCyRt7cyG5OeQd1aoVVs",
                "privKey": "+Nf61R1U4VCwbt1d9SXWvA7eF7sYZ2oBJ9e95Dr6a3s="
              },
              "lastRemoteEphemeralKey": "BWNsFPt7sptLQAEHoL9Kj0qZ4rtgEE/koGhOqxDhenQt",
              "previousCounter": 0,
              "rootKey": "eAIn+fJDkBPOaLrcoF0C0UawJlB0UOtEiMiOt4BdTzc="
            },
            "indexInfo": {
              "baseKey": "BeBmM7DvKkTUHyjXjY8fpIiPKN2GRZOLxkdeSfIW4U9j",
              "baseKeyType": 1,
              "closed": -1,
              "used": 1678883114850,
              "created": 1678883114850,
              "remoteIdentityKey": "BVipLbif1YSdDukn9T9F4NLkI1pBrCDwqgskrdOiNtIE"
            },
            "_chains": {
              "Bc+1+gB6tHZuu0UeKARUu94OQCyRt7cyG5OeQd1aoVVs": {
                "chainKey": {
                  "counter": 0,
                  "key": "3gW0ONGrK/RE8WJmTy/4eg80aqNnU/xlGBjC3vVmVKM="
                },
                "chainType": 1,
                "messageKeys": {}
              }
            },
            "pendingPreKey": {
              "signedKeyId": 2,
              "baseKey": "BeBmM7DvKkTUHyjXjY8fpIiPKN2GRZOLxkdeSfIW4U9j",
              "preKeyId": 4568149
            }
          }
        },
        "version": "v1"
      },
      "6281392128956.0": {
        "_sessions": {
          "BSdcT93PQrucd1xafYGEBNdkMmb5JFaVfkbQuhkgTI9r": {
            "registrationId": 1779675758,
            "currentRatchet": {
              "ephemeralKeyPair": {
                "pubKey": "BQQUprZdEe1TUEVMJrB7ysRQDWs9X040b9a3WU6cpskC",
                "privKey": "SDIDUmsijY5/sdaaRjLrt/bmJbhQuenuXZVJIldXXFw="
              },
              "lastRemoteEphemeralKey": "BXRF4YJ+1M27+ZE2yPbbM3wb2tfVXgjgPeHY129OsNUA",
              "previousCounter": 0,
              "rootKey": "/ZjYNxtnaipg3wvpRlDcQq//kQNe/YRO7ZN+QmWxXvM="
            },
            "indexInfo": {
              "baseKey": "BSdcT93PQrucd1xafYGEBNdkMmb5JFaVfkbQuhkgTI9r",
              "baseKeyType": 1,
              "closed": -1,
              "used": 1678883114856,
              "created": 1678883114856,
              "remoteIdentityKey": "BSYXR0pNUvwv/cgG/pqSVyijlIbEfRzDK/eVpjBAcBVh"
            },
            "_chains": {
              "BQQUprZdEe1TUEVMJrB7ysRQDWs9X040b9a3WU6cpskC": {
                "chainKey": {
                  "counter": 0,
                  "key": "twTpxVB5y0X248yCgIGENcMbHudGjUsdNvP8fyK/jJE="
                },
                "chainType": 1,
                "messageKeys": {}
              }
            },
            "pendingPreKey": {
              "signedKeyId": 15,
              "baseKey": "BSdcT93PQrucd1xafYGEBNdkMmb5JFaVfkbQuhkgTI9r",
              "preKeyId": 13236226
            }
          }
        },
        "version": "v1"
      },
      "6287784028546.0": {
        "_sessions": {
          "BcBPnt71yc+YKR0jk1Wf5qD2BK9jh6jtQ5HeryujOggm": {
            "registrationId": 1900696119,
            "currentRatchet": {
              "ephemeralKeyPair": {
                "pubKey": "BUadYvR5cachhrgF4FM0CQOw48Dh6nuU2ls8dxdntnUh",
                "privKey": "KOkOdOUfwTbj9jCtnjb5ZUYdBp/KFEpKwgPknpG4kWA="
              },
              "lastRemoteEphemeralKey": "BXIwPhDZKa9KN9iWYhCgf1+HzO7404R8kychuH+tC2wA",
              "previousCounter": 0,
              "rootKey": "N0DwUd/XcoVNC+c/hMR+Y8IDruf8YQ6OV7WO19nJXNE="
            },
            "indexInfo": {
              "baseKey": "BcBPnt71yc+YKR0jk1Wf5qD2BK9jh6jtQ5HeryujOggm",
              "baseKeyType": 1,
              "closed": -1,
              "used": 1678883114859,
              "created": 1678883114859,
              "remoteIdentityKey": "BWY8e2bC06vwygVSOZBtAH0o+G5D2V8+8uHhSlPW4T0F"
            },
            "_chains": {
              "BUadYvR5cachhrgF4FM0CQOw48Dh6nuU2ls8dxdntnUh": {
                "chainKey": {
                  "counter": 0,
                  "key": "V/xuk9XVGS21+XwPBpGSDZ95hUTJ089OMktXcU19cFo="
                },
                "chainType": 1,
                "messageKeys": {}
              }
            },
            "pendingPreKey": {
              "signedKeyId": 1,
              "baseKey": "BcBPnt71yc+YKR0jk1Wf5qD2BK9jh6jtQ5HeryujOggm",
              "preKeyId": 4689243
            }
          }
        },
        "version": "v1"
      }
    },
    "appStateSyncKeys": {
      "AAAAAKeM": {
        "keyData": "nA1vDPl0R8SfqlJ8miu83hc81l9mXXjiZo/zgMvrjeg=",
        "fingerprint": {
          "rawId": 1600505652,
          "currentIndex": 1,
          "deviceIndexes": [
            0,
            1
          ]
        },
        "timestamp": "1676276150171"
      },
      "AAAAAKeN": {
        "keyData": "J7xzE9Xi6p8vFVTD0CPIqruyyeFqaxtAlI/kXsmWlQU=",
        "fingerprint": {
          "rawId": 1600505652,
          "currentIndex": 1,
          "deviceIndexes": [
            0
          ]
        },
        "timestamp": "1677749691784"
      },
      "AAAAAKeK": {
        "keyData": "sok+cAfHra1FzkiS0uJ98B7QO/W1PGBerNC6QoEWUw4=",
        "fingerprint": {
          "rawId": 1600505651,
          "currentIndex": 1,
          "deviceIndexes": [
            0,
            1
          ]
        },
        "timestamp": "0"
      },
      "AAAAAKeL": {
        "keyData": "BcKj/edFM3HGsvwOyKBAo69d/b18rNLK/jAw6gb8IYE=",
        "fingerprint": {
          "rawId": 1600505651,
          "currentIndex": 1,
          "deviceIndexes": [
            0
          ]
        },
        "timestamp": "1676275887738"
      },
      "AAAAAKeQ": {
        "keyData": "iXqatSvndu3TxJqtW8JrJNX7EcHJYbzGUObia5oVXG0=",
        "fingerprint": {
          "rawId": 1600505654,
          "currentIndex": 1,
          "deviceIndexes": [
            0
          ]
        },
        "timestamp": "1678663837692"
      },
      "AAAAAKeR": {
        "keyData": "ls1OSJm3U7QWh0o8bEjxpGUI7Gh/QMfHwqNKdDakU98=",
        "fingerprint": {
          "rawId": 1600505655,
          "currentIndex": 1,
          "deviceIndexes": [
            0,
            1
          ]
        },
        "timestamp": "0"
      },
      "AAAAAKeO": {
        "keyData": "PSbCedRfZanMcs9W9IGtmqZ1wrJpoMpix9/8iFcbjYo=",
        "fingerprint": {
          "rawId": 1600505653,
          "currentIndex": 1,
          "deviceIndexes": [
            0,
            1
          ]
        },
        "timestamp": "0"
      },
      "AAAAAKeP": {
        "keyData": "fpQslI4B3S1+8e/xQfIqcx537qgRMwsGmiQgrBXzjc0=",
        "fingerprint": {
          "rawId": 1600505654,
          "currentIndex": 1,
          "deviceIndexes": [
            0,
            1
          ]
        },
        "timestamp": "0"
      }
    },
    "appStateVersions": {
      "regular": null,
      "regular_low": null,
      "regular_high": null,
      "critical_block": null,
      "critical_unblock_low": null
    },
    "senderKeys": {
      "120363030444365532@g.us::6281333154367::0": [
        {
          "senderKeyId": 1393236238,
          "senderChainKey": {
            "iteration": 27,
            "seed": "OlcR22pkJaYlxDEHOMW4KX9Cu1DdoRtNCDFyCC8QcpI="
          },
          "senderSigningKey": {
            "public": "BUrjjY1Ph2Fg8YhRGDnhymHqDz1vwC2jTvYRSFuusphH"
          }
        }
      ],
      "120363030444365532@g.us::6281327238906:28::0": [
        {
          "senderKeyId": 13878607,
          "senderChainKey": {
            "iteration": 3,
            "seed": "4tsWXZJuxliRmBexVQ+l1dU27yJt0R5dDGxx3UWBojI="
          },
          "senderSigningKey": {
            "public": "BZ1RmHfagfSL6Q/91kP7p+bE0WVdul8X+7cvAEfPgRdn",
            "private": "uFZpXflZiRQ7zH/rh6PSt8OtoiSAuNvZW5zThmKXmFk="
          }
        }
      ],
      "120363030444365532@g.us::6287784028546:4::0": [
        {
          "senderKeyId": 1384550193,
          "senderChainKey": {
            "iteration": 192,
            "seed": "HusvglG4FWikSZxS8SsKo4qaSeuvtGT4SNmWet1E6pg="
          },
          "senderSigningKey": {
            "public": "BT3lR8249M8dO/n4soIiJl70KLFXeqJa5Xqsao0zuR8w"
          }
        }
      ],
      "120363030444365532@g.us::6281349838609:9::0": [
        {
          "senderKeyId": 1332862931,
          "senderChainKey": {
            "iteration": 21,
            "seed": "+b4tpBLqQu3yrESGirSWIKbaQ5yI1fFPDH4/oBQ8Jlo="
          },
          "senderSigningKey": {
            "public": "Bfsx0vlNQiO/77CmznFIWUe/ozS9WbcIF2/j8FBraGQk"
          }
        }
      ]
    },
    "senderKeyMemory": {
      "120363030444365532@g.us": {
        "6287784028546@s.whatsapp.net": true,
        "6287784028546:4@s.whatsapp.net": true,
        "6281392128956@s.whatsapp.net": true,
        "6281349838609@s.whatsapp.net": true,
        "6281349838609:9@s.whatsapp.net": true,
        "6281333154367@s.whatsapp.net": true,
        "6281327238906@s.whatsapp.net": true
      }
    }
  }
}
